KratosMultiphysics/PoromechanicsApplication/__init__.py
KratosMultiphysics/PoromechanicsApplication/apply_normal_load_table_process.py
KratosMultiphysics/PoromechanicsApplication/apply_scalar_constraint_table_process.py
KratosMultiphysics/PoromechanicsApplication/apply_vector_constraint_table_process.py
KratosMultiphysics/PoromechanicsApplication/check_and_prepare_model_process_poro.py
KratosMultiphysics/PoromechanicsApplication/periodic_interface_activation_process.py
KratosMultiphysics/PoromechanicsApplication/poromechanics_U_Pl_explicit_dynamic_solver.py
KratosMultiphysics/PoromechanicsApplication/poromechanics_U_Pl_solver.py
KratosMultiphysics/PoromechanicsApplication/poromechanics_analysis.py
KratosMultiphysics/PoromechanicsApplication/poromechanics_cleaning_utility.py
KratosMultiphysics/PoromechanicsApplication/poromechanics_face_load_control_module_process.py
KratosMultiphysics/PoromechanicsApplication/poromechanics_fracture_propagation_utility.py
KratosMultiphysics/PoromechanicsApplication/poromechanics_initial_stress_utility.py
KratosMultiphysics/.libs/KratosPoromechanicsApplication.pyd
KratosMultiphysics/.libs/KratosPoromechanicsCore.dll
KratosMultiphysics/.libs/KratosPoromechanicsCore.lib
kratosporomechanicsapplication-10.4.0.dist-info/METADATA
kratosporomechanicsapplication-10.4.0.dist-info/WHEEL
kratosporomechanicsapplication-10.4.0.dist-info/RECORD
